Task 3 /RTL/gpio_ctrl.v
module gpio_ip (
    input wire clk,
    input wire resetn,

    input wire [29:0] mem_wordaddr,
    input wire        isIO,
    input wire        mem_wstrb,
    input wire [31:0] mem_wdata,

    output wire [31:0] gpio_rdata,
    output wire [31:0] gpio_out
);

    // GPIO address bit
    wire sel_data = mem_wordaddr[3];
    wire sel_dir  = mem_wordaddr[4];
    wire sel_read = mem_wordaddr[5];

    // Internal register
    reg [31:0] gpio_data;
    reg [31:0] gpio_dir;

    // WRITE LOGIC
    always @(posedge clk) begin
    if(!resetn) begin
        gpio_data <= 32'b0;
        gpio_dir  <= 32'b0;
    end
    else if(isIO && mem_wstrb) begin

        if(sel_data)
            gpio_data <= mem_wdata;

        if(sel_dir)
            gpio_dir <= mem_wdata;

    end
    end

    // OUTPUT CONNECTION
    assign gpio_out = gpio_data & gpio_dir;

    // READBACK LOGIC
    
    assign gpio_rdata =
        sel_data ? gpio_data :
        sel_dir  ? gpio_dir  :
        sel_read ? gpio_read :
        32'b0;
        
     // Read Logic  
    wire [31:0] gpio_read;

    assign gpio_read = (gpio_data & gpio_dir);

endmodule

Task 3/RTL/tb_gpio_ctrl.v
`timescale 1ns/1ps
`default_nettype none

`include "gpio_ctrl.v"

module tb_gpio;

    reg clk = 0;
    reg resetn = 0;

    always #5 clk = ~clk;

    reg  [29:0] mem_wordaddr;
    reg         isIO;
    reg         mem_wstrb;
    reg  [31:0] mem_wdata;

    wire [31:0] gpio_rdata;
    wire [31:0] gpio_out;

    gpio_ip DUT (
        .clk(clk),
        .resetn(resetn),

        .mem_wordaddr(mem_wordaddr),
        .isIO(isIO),
        .mem_wstrb(mem_wstrb),
        .mem_wdata(mem_wdata),

        .gpio_rdata(gpio_rdata),
        .gpio_out(gpio_out)
    );

    //--------------------------------------------------
    // Waveform
    //--------------------------------------------------

    initial begin
        $dumpfile("gpio_task3.vcd");
        $dumpvars(0,tb_gpio);
    end

    //--------------------------------------------------
    // Address Decode
    //--------------------------------------------------

    localparam GPIO_DATA_ADDR = 30'b000000000000000000000000001000;
    localparam GPIO_DIR_ADDR  = 30'b000000000000000000000000010000;
    localparam GPIO_READ_ADDR = 30'b000000000000000000000000100000;

    integer pass_count = 0;
    integer fail_count = 0;

    //--------------------------------------------------
    // WRITE TASK
    //--------------------------------------------------

    task write_reg;
        input [29:0] addr;
        input [31:0] data;
        begin
            @(negedge clk);

            mem_wordaddr = addr;
            mem_wdata    = data;
            isIO         = 1'b1;
            mem_wstrb    = 1'b1;

            @(posedge clk);
            #1;

            mem_wstrb = 0;
            isIO      = 0;
        end
    endtask

    //--------------------------------------------------
    // CHECK TASK
    //--------------------------------------------------

    task check_reg;
        input [29:0] addr;
        input [31:0] expected;
        input integer testnum;

        begin

            mem_wordaddr = addr;
            isIO         = 1'b1;
            mem_wstrb    = 1'b0;

            #1;

            $write(
                "Test %0d | Expected = 0x%08X | Read = 0x%08X | ",
                testnum,
                expected,
                gpio_rdata
            );

            if(gpio_rdata === expected)
            begin
                $display("PASS");
                pass_count = pass_count + 1;
            end
            else
            begin
                $display("FAIL");
                fail_count = fail_count + 1;
            end

            isIO = 0;

        end
    endtask

    //--------------------------------------------------
    // MAIN TEST
    //--------------------------------------------------

    initial begin

        mem_wordaddr = 0;
        mem_wdata    = 0;
        isIO         = 0;
        mem_wstrb    = 0;

        //----------------------------------------------
        // RESET
        //----------------------------------------------

        resetn = 0;

        repeat(4) @(posedge clk);

        resetn = 1;

        repeat(2) @(posedge clk);

        $display("");
        $display("=====================================");
        $display(" GPIO TASK-3 TEST START");
        $display("=====================================");

        //----------------------------------------------
        // TEST 1 : DATA RESET
        //----------------------------------------------

        check_reg(GPIO_DATA_ADDR,32'h00000000,1);

        //----------------------------------------------
        // TEST 2 : DIR RESET
        //----------------------------------------------

        check_reg(GPIO_DIR_ADDR,32'h00000000,2);

        //----------------------------------------------
        // TEST 3 : WRITE DATA
        //----------------------------------------------

        write_reg(GPIO_DATA_ADDR,32'hAAAAAAAA);

        check_reg(GPIO_DATA_ADDR,32'hAAAAAAAA,3);

        //----------------------------------------------
        // TEST 4 : WRITE DIR
        //----------------------------------------------

        write_reg(GPIO_DIR_ADDR,32'hFFFFFFFF);

        check_reg(GPIO_DIR_ADDR,32'hFFFFFFFF,4);

        //----------------------------------------------
        // TEST 5 : READ REGISTER
        //----------------------------------------------

        check_reg(GPIO_READ_ADDR,32'hAAAAAAAA,5);

        //----------------------------------------------
        // TEST 6 : CHANGE DATA
        //----------------------------------------------

        write_reg(GPIO_DATA_ADDR,32'h55555555);

        check_reg(GPIO_READ_ADDR,32'h55555555,6);

        //----------------------------------------------
        // TEST 7 : LED OUTPUT
        //----------------------------------------------

        $write(
            "Test 7 | gpio_out = 0x%08X | ",
            gpio_out
        );

        if(gpio_out === 32'h55555555)
        begin
            $display("PASS");
            pass_count = pass_count + 1;
        end
        else
        begin
            $display("FAIL");
            fail_count = fail_count + 1;
        end

        //----------------------------------------------
        // TEST 8 : Direction Masking
        //----------------------------------------------

        write_reg(GPIO_DIR_ADDR,32'h0000001F);

        write_reg(GPIO_DATA_ADDR,32'hFFFFFFFF);

        check_reg(GPIO_READ_ADDR,32'h0000001F,8);

        //----------------------------------------------
        // TEST 9 : Invalid Access
        //----------------------------------------------

        @(negedge clk);

        mem_wordaddr = GPIO_DATA_ADDR;
        mem_wdata    = 32'hDEADBEEF;
        mem_wstrb    = 1'b1;
        isIO         = 1'b0;

        @(posedge clk);
        #1;

        mem_wstrb = 0;

        check_reg(GPIO_DATA_ADDR,32'hFFFFFFFF,9);

        //----------------------------------------------
        // RESULTS
        //----------------------------------------------

        repeat(2) @(posedge clk);

        $display("");
        $display("=====================================");
        $display(" PASSED = %0d", pass_count);
        $display(" FAILED = %0d", fail_count);
        $display("=====================================");

        $finish;

    end

    //--------------------------------------------------
    // TIMEOUT
    //--------------------------------------------------

    initial begin

        #10000;

        $display("TIMEOUT");

        $finish;

    end

endmodule

Task 3 /RTL/gpio_task3.vcd
$date
	Sun May 31 23:43:20 2026
$end
$version
	Icarus Verilog
$end
$timescale
	1ps
$end
$scope module tb_gpio $end
$var wire 32 ! gpio_rdata [31:0] $end
$var wire 32 " gpio_out [31:0] $end
$var parameter 30 # GPIO_DATA_ADDR $end
$var parameter 30 $ GPIO_DIR_ADDR $end
$var parameter 30 % GPIO_READ_ADDR $end
$var reg 1 & clk $end
$var reg 1 ' isIO $end
$var reg 32 ( mem_wdata [31:0] $end
$var reg 30 ) mem_wordaddr [29:0] $end
$var reg 1 * mem_wstrb $end
$var reg 1 + resetn $end
$var integer 32 , fail_count [31:0] $end
$var integer 32 - pass_count [31:0] $end
$scope module DUT $end
$var wire 1 & clk $end
$var wire 32 . gpio_out [31:0] $end
$var wire 32 / gpio_read [31:0] $end
$var wire 1 ' isIO $end
$var wire 32 0 mem_wdata [31:0] $end
$var wire 30 1 mem_wordaddr [29:0] $end
$var wire 1 * mem_wstrb $end
$var wire 1 + resetn $end
$var wire 1 2 sel_read $end
$var wire 1 3 sel_dir $end
$var wire 1 4 sel_data $end
$var wire 32 5 gpio_rdata [31:0] $end
$var reg 32 6 gpio_data [31:0] $end
$var reg 32 7 gpio_dir [31:0] $end
$upscope $end
$scope task check_reg $end
$var reg 30 8 addr [29:0] $end
$var reg 32 9 expected [31:0] $end
$var integer 32 : testnum [31:0] $end
$upscope $end
$scope task write_reg $end
$var reg 30 ; addr [29:0] $end
$var reg 32 < data [31:0] $end
$upscope $end
$upscope $end
$enddefinitions $end
$comment Show the parameter values. $end
$dumpall
b100000 %
b10000 $
b1000 #
$end
#0
$dumpvars
bx <
bx ;
bx :
bx 9
bx 8
bx 7
bx 6
b0 5
04
03
02
b0 1
b0 0
bx /
bx .
b0 -
b0 ,
0+
0*
b0 )
b0 (
0'
0&
bx "
b0 !
$end
#5000
b0 /
b0 "
b0 .
b0 7
b0 6
1&
#10000
0&
#15000
1&
#20000
0&
#25000
1&
#30000
0&
#35000
1+
1&
#40000
0&
#45000
1&
#50000
0&
#55000
14
1'
b1000 )
b1000 1
b1 :
b0 9
b1000 8
1&
#56000
04
13
b10000 )
b10000 1
b10 :
b10000 8
1'
b1 -
#57000
b10101010101010101010101010101010 <
b1000 ;
0'
b10 -
#60000
14
03
1*
1'
b10101010101010101010101010101010 (
b10101010101010101010101010101010 0
b1000 )
b1000 1
0&
#65000
b10101010101010101010101010101010 !
b10101010101010101010101010101010 5
b10101010101010101010101010101010 6
1&
#66000
b11 :
b10101010101010101010101010101010 9
b1000 8
1'
0*
#67000
b11111111111111111111111111111111 <
b10000 ;
0'
b11 -
#70000
b0 !
b0 5
04
13
1*
1'
b11111111111111111111111111111111 (
b11111111111111111111111111111111 0
b10000 )
b10000 1
0&
#75000
b11111111111111111111111111111111 !
b11111111111111111111111111111111 5
b10101010101010101010101010101010 /
b10101010101010101010101010101010 "
b10101010101010101010101010101010 .
b11111111111111111111111111111111 7
1&
#76000
b100 :
b11111111111111111111111111111111 9
b10000 8
1'
0*
#77000
b10101010101010101010101010101010 !
b10101010101010101010101010101010 5
03
12
b100000 )
b100000 1
b101 :
b10101010101010101010101010101010 9
b100000 8
1'
b100 -
#78000
b1010101010101010101010101010101 <
b1000 ;
0'
b101 -
#80000
14
02
1*
1'
b1010101010101010101010101010101 (
b1010101010101010101010101010101 0
b1000 )
b1000 1
0&
#85000
b1010101010101010101010101010101 !
b1010101010101010101010101010101 5
b1010101010101010101010101010101 /
b1010101010101010101010101010101 "
b1010101010101010101010101010101 .
b1010101010101010101010101010101 6
1&
#86000
b1010101010101010101010101010101 !
b1010101010101010101010101010101 5
04
12
b100000 )
b100000 1
b110 :
b1010101010101010101010101010101 9
1'
0*
#87000
b11111 <
b10000 ;
0'
b111 -
#90000
b11111111111111111111111111111111 !
b11111111111111111111111111111111 5
13
02
1*
1'
b11111 (
b11111 0
b10000 )
b10000 1
0&
#95000
b11111 !
b11111 5
b10101 /
b10101 "
b10101 .
b11111 7
1&
#96000
b11111111111111111111111111111111 <
b1000 ;
0'
0*
#100000
b1010101010101010101010101010101 !
b1010101010101010101010101010101 5
14
03
1*
1'
b11111111111111111111111111111111 (
b11111111111111111111111111111111 0
b1000 )
b1000 1
0&
#105000
b11111111111111111111111111111111 !
b11111111111111111111111111111111 5
b11111 /
b11111 "
b11111 .
b11111111111111111111111111111111 6
1&
#106000
b11111 !
b11111 5
04
12
b100000 )
b100000 1
b1000 :
b11111 9
1'
0*
#107000
0'
b1000 -
#110000
b11111111111111111111111111111111 !
b11111111111111111111111111111111 5
14
02
1*
b11011110101011011011111011101111 (
b11011110101011011011111011101111 0
b1000 )
b1000 1
0&
#115000
1&
#116000
1'
b1001 :
b11111111111111111111111111111111 9
b1000 8
0*
#117000
0'
b1001 -
