Task 2/RTL/gpio_ip.v
module gpio_ip (
    input wire clk,
    input wire resetn,

    input wire [29:0] mem_wordaddr,
    input wire        isIO,
    input wire        mem_wstrb,
    input wire [31:0] mem_wdata,

    output reg [31:0] gpio_rdata,
    output reg [31:0] gpio_out
);

    // GPIO address bit
    localparam IO_GPIO_bit = 3;

    // Internal register
    reg [31:0] gpio_reg;

    // WRITE LOGIC
    always @(posedge clk) begin
        if(!resetn) begin
            gpio_reg <= 32'b0;
        end
        else if(isIO &&
                mem_wstrb &&
                mem_wordaddr[IO_GPIO_bit]) begin

            gpio_reg <= mem_wdata;
        end
    end

    // OUTPUT CONNECTION
    always @(*) begin
    gpio_out = gpio_reg;
end

    // READBACK LOGIC
    always @(*) begin
        if(isIO && mem_wordaddr[IO_GPIO_bit])
            gpio_rdata = gpio_reg;
        else
            gpio_rdata = 32'b0;
    end

endmodule

Task 2/tb_gpio.v
`timescale 1ns/1ps
`default_nettype none

`include "gpio_ip.v"

module tb_gpio;

    reg clk    = 0;
    reg resetn = 0;

    // 100 MHz clock
    always #5 clk = ~clk;

    reg  [29:0] mem_wordaddr;
    reg         isIO;
    reg         mem_wstrb;
    reg  [31:0] mem_wdata;

    wire [31:0] gpio_rdata;
    wire [31:0] gpio_out;

    // DUT
    gpio_ip DUT (
        .clk(clk),
        .resetn(resetn),

        .mem_wordaddr(mem_wordaddr),
        .isIO(isIO),
        .mem_wstrb(mem_wstrb),
        .mem_wdata(mem_wdata),

        .gpio_rdata(gpio_rdata),
        .gpio_out(gpio_out)
    );

    // Waveform dump
    initial begin
        $dumpfile("gpio_wave.vcd");
        $dumpvars(0, tb_gpio);
    end

    integer pass_count = 0;
    integer fail_count = 0;

    // =====================================================
    // GPIO WRITE TASK
    // =====================================================

    task gpio_write;
        input [31:0] data;
        begin
            @(negedge clk);

            mem_wordaddr = 30'b1000; // GPIO bit = 3
            isIO         = 1'b1;
            mem_wstrb    = 1'b1;
            mem_wdata    = data;

            @(posedge clk);
            #1;

            mem_wstrb = 1'b0;
            isIO      = 1'b0;
        end
    endtask

    // =====================================================
    // CHECK TASK
    // =====================================================

    task check_gpio;
        input [31:0] expected;
        input integer test_num;

        begin
            mem_wordaddr = 30'b1000;
            isIO         = 1'b1;
            mem_wstrb    = 1'b0;

            #1;

            $write(
                "Test %0d | wrote 0x%08X | gpio_out=0x%08X | gpio_rdata=0x%08X | ",
                test_num,
                expected,
                gpio_out,
                gpio_rdata
            );

            if(gpio_out === expected &&
               gpio_rdata === expected) begin

                $display("PASS");
                pass_count = pass_count + 1;

            end else begin

                $display("FAIL  *** expected 0x%08X ***", expected);
                fail_count = fail_count + 1;
            end

            isIO = 1'b0;
        end
    endtask

    // =====================================================
    // MAIN TEST
    // =====================================================

    initial begin

        mem_wordaddr = 0;
        isIO         = 0;
        mem_wstrb    = 0;
        mem_wdata    = 0;

        // RESET
        resetn = 0;

        repeat(4) @(posedge clk);

        resetn = 1;

        repeat(2) @(posedge clk);

        $display("============================================");
        $display("   GPIO IP Testbench — Starting Tests");
        $display("============================================");

        // RESET CHECK
        $write(
            "Reset check  | gpio_out after reset = 0x%08X | ",
            gpio_out
        );

        if(gpio_out === 32'h00000000) begin
            $display("PASS (cleared to 0)");
            pass_count = pass_count + 1;
        end
        else begin
            $display("FAIL (expected 0x00000000)");
            fail_count = fail_count + 1;
        end

        // TEST CASES

        gpio_write(32'h00000000);
        check_gpio(32'h00000000, 1);

        gpio_write(32'hFFFFFFFF);
        check_gpio(32'hFFFFFFFF, 2);

        gpio_write(32'h00000001);
        check_gpio(32'h00000001, 3);

        gpio_write(32'h80000000);
        check_gpio(32'h80000000, 4);

        gpio_write(32'hAAAAAAAA);
        check_gpio(32'hAAAAAAAA, 5);

        gpio_write(32'h55555555);
        check_gpio(32'h55555555, 6);

        gpio_write(32'hDEADBEEF);
        check_gpio(32'hDEADBEEF, 7);

        // Overwrite test
        gpio_write(32'hCAFEBABE);
        gpio_write(32'h12345678);

        check_gpio(32'h12345678, 8);

        // Invalid write test
        @(negedge clk);

        mem_wordaddr = 30'b1000;
        isIO         = 1'b0;
        mem_wstrb    = 1'b1;
        mem_wdata    = 32'hBAD0BAD0;

        @(posedge clk);

        #1;

        mem_wstrb = 1'b0;

        $write(
            "Test 9 | isIO=0 write ignored | gpio_out=0x%08X | ",
            gpio_out
        );

        if(gpio_out === 32'h12345678) begin
            $display("PASS (register unchanged)");
            pass_count = pass_count + 1;
        end
        else begin
            $display("FAIL (register incorrectly overwritten)");
            fail_count = fail_count + 1;
        end

        repeat(2) @(posedge clk);

        $display("============================================");
        $display(
            "Results: %0d PASSED, %0d FAILED",
            pass_count,
            fail_count
        );

        $display("Waveform saved to: gpio_wave.vcd");
        $display("============================================");

        $finish;
    end

    // Timeout protection
    initial begin
        #10000;

        $display("TIMEOUT — simulation exceeded 10us");

        $finish;
    end

endmodule

Task 2/RTL/gpio_wave.vcd
$date
	Wed May 27 20:53:06 2026
$end
$version
	Icarus Verilog
$end
$timescale
	1ps
$end
$scope module tb_gpio $end
$var wire 32 ! gpio_rdata [31:0] $end
$var wire 32 " gpio_out [31:0] $end
$var reg 1 # clk $end
$var reg 1 $ isIO $end
$var reg 32 % mem_wdata [31:0] $end
$var reg 30 & mem_wordaddr [29:0] $end
$var reg 1 ' mem_wstrb $end
$var reg 1 ( resetn $end
$var integer 32 ) fail_count [31:0] $end
$var integer 32 * pass_count [31:0] $end
$scope module DUT $end
$var wire 1 # clk $end
$var wire 1 $ isIO $end
$var wire 32 + mem_wdata [31:0] $end
$var wire 30 , mem_wordaddr [29:0] $end
$var wire 1 ' mem_wstrb $end
$var wire 1 ( resetn $end
$var parameter 32 - IO_GPIO_bit $end
$var reg 32 . gpio_out [31:0] $end
$var reg 32 / gpio_rdata [31:0] $end
$var reg 32 0 gpio_reg [31:0] $end
$upscope $end
$scope task check_gpio $end
$var reg 32 1 expected [31:0] $end
$var integer 32 2 test_num [31:0] $end
$upscope $end
$scope task gpio_write $end
$var reg 32 3 data [31:0] $end
$upscope $end
$upscope $end
$enddefinitions $end
$comment Show the parameter values. $end
$dumpall
b11 -
$end
#0
$dumpvars
bx 3
bx 2
bx 1
bx 0
b0 /
bx .
b0 ,
b0 +
b0 *
b0 )
0(
0'
b0 &
b0 %
0$
0#
bx "
b0 !
$end
#5000
b0 "
b0 .
b0 0
1#
#10000
0#
#15000
1#
#20000
0#
#25000
1#
#30000
0#
#35000
1(
1#
#40000
0#
#45000
1#
#50000
0#
#55000
b0 3
b1 *
1#
#60000
1'
1$
b1000 &
b1000 ,
0#
#65000
1#
#66000
b1 2
b0 1
1$
0'
#67000
b11111111111111111111111111111111 3
0$
b10 *
#70000
b11111111111111111111111111111111 %
b11111111111111111111111111111111 +
1'
1$
0#
#75000
b11111111111111111111111111111111 !
b11111111111111111111111111111111 /
b11111111111111111111111111111111 "
b11111111111111111111111111111111 .
b11111111111111111111111111111111 0
1#
#76000
b10 2
b11111111111111111111111111111111 1
1$
0'
#77000
b0 !
b0 /
b1 3
0$
b11 *
#80000
b11111111111111111111111111111111 !
b11111111111111111111111111111111 /
b1 %
b1 +
1'
1$
0#
#85000
b1 !
b1 /
b1 "
b1 .
b1 0
1#
#86000
b11 2
b1 1
1$
0'
#87000
b0 !
b0 /
b10000000000000000000000000000000 3
0$
b100 *
#90000
b1 !
b1 /
b10000000000000000000000000000000 %
b10000000000000000000000000000000 +
1'
1$
0#
#95000
b10000000000000000000000000000000 !
b10000000000000000000000000000000 /
b10000000000000000000000000000000 "
b10000000000000000000000000000000 .
b10000000000000000000000000000000 0
1#
#96000
b100 2
b10000000000000000000000000000000 1
1$
0'
#97000
b0 !
b0 /
b10101010101010101010101010101010 3
0$
b101 *
#100000
b10000000000000000000000000000000 !
b10000000000000000000000000000000 /
b10101010101010101010101010101010 %
b10101010101010101010101010101010 +
1'
1$
0#
#105000
b10101010101010101010101010101010 !
b10101010101010101010101010101010 /
b10101010101010101010101010101010 "
b10101010101010101010101010101010 .
b10101010101010101010101010101010 0
1#
#106000
b101 2
b10101010101010101010101010101010 1
1$
0'
#107000
b0 !
b0 /
b1010101010101010101010101010101 3
0$
b110 *
#110000
b10101010101010101010101010101010 !
b10101010101010101010101010101010 /
b1010101010101010101010101010101 %
b1010101010101010101010101010101 +
1'
1$
0#
#115000
b1010101010101010101010101010101 !
b1010101010101010101010101010101 /
b1010101010101010101010101010101 "
b1010101010101010101010101010101 .
b1010101010101010101010101010101 0
1#
#116000
b110 2
b1010101010101010101010101010101 1
1$
0'
#117000
b0 !
b0 /
b11011110101011011011111011101111 3
0$
b111 *
#120000
b1010101010101010101010101010101 !
b1010101010101010101010101010101 /
b11011110101011011011111011101111 %
b11011110101011011011111011101111 +
1'
1$
0#
#125000
b11011110101011011011111011101111 !
b11011110101011011011111011101111 /
b11011110101011011011111011101111 "
b11011110101011011011111011101111 .
b11011110101011011011111011101111 0
1#
#126000
b111 2
b11011110101011011011111011101111 1
1$
0'
#127000
b0 !
b0 /
b11001010111111101011101010111110 3
0$
b1000 *
#130000
b11011110101011011011111011101111 !
b11011110101011011011111011101111 /
b11001010111111101011101010111110 %
b11001010111111101011101010111110 +
1'
1$
0#
#135000
b11001010111111101011101010111110 !
b11001010111111101011101010111110 /
b11001010111111101011101010111110 "
b11001010111111101011101010111110 .
b11001010111111101011101010111110 0
1#
#136000
b0 !
b0 /
b10010001101000101011001111000 3
0$
0'
#140000
b11001010111111101011101010111110 !
b11001010111111101011101010111110 /
b10010001101000101011001111000 %
b10010001101000101011001111000 +
1'
1$
0#
#145000
b10010001101000101011001111000 !
b10010001101000101011001111000 /
b10010001101000101011001111000 "
b10010001101000101011001111000 .
b10010001101000101011001111000 0
1#
#146000
b1000 2
b10010001101000101011001111000 1
1$
0'
#147000
b0 !
b0 /
0$
b1001 *
#150000
b10111010110100001011101011010000 %
b10111010110100001011101011010000 +
1'
0#
#155000
1#
#156000
b1010 *
0'
